tsiconv/__init__.py
tsiconv/__main__.py
tsiconv-1.0.0.dist-info/entry_points.txt
tsiconv-1.0.0.dist-info/WHEEL
tsiconv-1.0.0.dist-info/METADATA
tsiconv-1.0.0.dist-info/RECORD
