Metadata-Version: 2.1
Name: tsiconv
Version: 1.0.0
Summary: convert an input time to UTC (optionally a destination timezone).
Home-page: https://github.com/tbennett6421/tsiconv
Author: Tyler Bennett
Author-email: tbennett6421@gmail.com
Requires-Python: >=3.8.0,<4.0.0
Classifier: Environment :: Console
Classifier: Programming Language :: Python :: 3
Classifier: Programming Language :: Python :: 3.8
Classifier: Programming Language :: Python :: 3.9
Classifier: Topic :: Security
Requires-Dist: python-dateutil (>=2.8.2,<3.0.0)
Requires-Dist: pytz (>=2021.3,<2022.0)
Project-URL: Repository, https://github.com/tbennett6421/tsiconv
